{
	"items": [
		{ "id": 65038, "enchant": 4206, "gems": [52293, 52224] },
		{ "id": 60227, "gems": [52219] },
		{ "id": 65228, "enchant": 4198, "gems": [52224], "reforging": 126 },
		{ "id": 69878, "randomSuffix": -128, "enchant": 4090, "reforging": 122 },
		{ "id": 65224, "enchant": 4103, "gems": [52221, 52231], "reforging": 129 },
		{ "id": 65143, "enchant": 3850, "gems": [0] },
		{ "id": 65119, "enchant": 4107, "gems": [52219, 0] },
		{ "id": 65086, "gems": [52219, 52219], "reforging": 122 },
		{ "id": 65217, "enchant": 4270, "gems": [52219, 52219] },
		{ "id": 65075, "enchant": 4094, "gems": [52231] },
		{ "id": 60226, "gems": [52219], "reforging": 144 },
		{ "id": 65372, "randomSuffix": -125 },
		{ "id": 58483, "gems": [52219] },
		{ "id": 62471 },
		{ "id": 65036, "enchant": 4098, "reforging": 129 },
		{ "id": 65023, "enchant": 4085 },
		{ "id": 64676, "gems": [52219], "reforging": 122 }
	]
}
